scandb/__init__.py
scandb/compare.py
scandb/importer/__init__.py
scandb/importer/cli.py
scandb/importer/nessus.py
scandb/importer/nmap.py
scandb/importer/util.py
scandb/models/__init__.py
scandb/models/db.py
scandb/models/report.py
scandb/report/__init__.py
scandb/report/cli.py
scandb/report/queries.py
scandb/report/util.py
scandb/services/__init__.py
scandb/services/cli.py
scandb/services/queries.py
scandb/statistics/__init__.py
scandb/statistics/cli.py
scandb/statistics/queries.py
scandb/vulns/__init__.py
scandb/vulns/cli.py
scandb/vulns/queries.py
scandb-1.2.1.dist-info/METADATA
scandb-1.2.1.dist-info/WHEEL
scandb-1.2.1.dist-info/entry_points.txt
scandb-1.2.1.dist-info/top_level.txt
scandb-1.2.1.dist-info/RECORD
