Metadata-Version: 2.1
Name: scandb
Version: 1.2.1
Summary: Scripts to import nmap and nessus scan results into a SQLite database, analyze the overall results and generate reports or target lists.
Home-page: https://github.com/c-bless/scandb
Author: Christoph Bless
Author-email: github@cbless.de
License: GPLv3
Requires-Dist: argparse
Requires-Dist: termcolor
Requires-Dist: python-libnmap
Requires-Dist: python-libnessus
Requires-Dist: SQLAlchemy <2.0.0
Requires-Dist: sqlalchemy-views
Requires-Dist: docxtpl
